{"componentChunkName":"component---src-components-background-template-tsx","path":"/game:garou-mark-of-the-wolves/kevin","webpackCompilationHash":"43fd0416cd1c49d45208","result":{"data":{"currentLevel":{"levelName":"Kevin","gameNameUsa":"Garou: Mark of the Wolves","developer":"SNK","system":"Neo Geo","year":1999,"series":"Fatal Fury"},"prevLevel":{"levelName":"Team Psycho Soldiers","gameNameUsa":"The King of Fighters '95"},"nextLevel":{"levelName":"Town at Night","gameNameUsa":"The Last Blade 2"},"mainImg":{"publicURL":"/static/motw_kevin-c2a9a33fe2108798d0b622867e9ab727.gif"},"bgImg":{"childImageSharp":{"resize":{"src":"/static/48e8306ce4134247674afd3a7ee9bddb/ad8a7/motw_kevin_static.jpg"}}},"twitterImg":{"childImageSharp":{"resize":{"src":"/static/48e8306ce4134247674afd3a7ee9bddb/e7081/motw_kevin_static.jpg"}}},"dimensions":{"width":"623","height":"384"}},"pageContext":{"isCreatedByStatefulCreatePages":false,"currentId":24,"nextId":264,"prevId":54,"mainImageRelativePath":"bgs/full/motw_kevin.gif","bgImageRelativePath":"bgs/static/motw_kevin_static.jpg","mainImageRegex":"/motw_kevin.gif/"}}}