{"componentChunkName":"component---src-components-background-template-tsx","path":"/game:world-heroes-2/rasputen","webpackCompilationHash":"be3257431df42ebf1d66","result":{"data":{"currentLevel":{"levelName":"Rasputen","gameNameUsa":"World Heroes 2","developer":"ADK","system":"Neo Geo","year":1993,"series":"World Heroes","ripCredit":null,"ripCreditUrl":null},"prevLevel":{"levelName":"Museum","gameNameUsa":"The King of Fighters '99"},"nextLevel":{"levelName":"Santana","gameNameUsa":"Art of Fighting 3"},"mainImg":{"publicURL":"/static/wh2_rasputen-5a8bbcdf51aa08c808ac6d5971550d3b.gif"},"bgImg":{"childImageSharp":{"resize":{"src":"/static/3f44d09ecc1621827f5535339f184726/ad8a7/wh2_rasputen_static.jpg"}}},"twitterImg":{"childImageSharp":{"fixed":{"src":"/static/3f44d09ecc1621827f5535339f184726/792e8/wh2_rasputen_static.jpg"}}},"dimensions":{"width":"640","height":"256"}},"pageContext":{"isCreatedByStatefulCreatePages":false,"currentId":356,"nextId":257,"prevId":72,"mainImageRelativePath":"bgs/full/wh2_rasputen.gif","bgImageRelativePath":"bgs/static/wh2_rasputen_static.jpg","mainImageRegex":"/wh2_rasputen.gif/"}}}