{"componentChunkName":"component---src-components-background-template-tsx","path":"/game:the-king-of-fighters-xiii/france/fullscreen","webpackCompilationHash":"43fd0416cd1c49d45208","result":{"data":{"currentLevel":{"levelName":"France","gameNameUsa":"The King of Fighters XIII","developer":"SNK Playmore","system":"X2","year":2010,"series":"King of Fighters"},"prevLevel":{"levelName":"Kaede","gameNameUsa":"The Last Blade 2"},"nextLevel":{"levelName":"Team Japan","gameNameUsa":"The King of Fighters '94"},"mainImg":{"publicURL":"/static/kof13_france-77ae4af6e4c248675912205baf556769.jpg"},"bgImg":{"childImageSharp":{"resize":{"src":"/static/4746fba9bae21961151e607687106b94/ad8a7/kof13_france_static.jpg"}}},"twitterImg":{"childImageSharp":{"resize":{"src":"/static/4746fba9bae21961151e607687106b94/e7081/kof13_france_static.jpg"}}},"dimensions":{"width":"2560","height":"820"}},"pageContext":{"isCreatedByStatefulCreatePages":false,"currentId":81,"nextId":49,"prevId":262,"mainImageRelativePath":"bgs/full/kof13_france.jpg","bgImageRelativePath":"bgs/static/kof13_france_static.jpg","mainImageRegex":"/kof13_france.jpg/","fullscreen":true}}}