{"componentChunkName":"component---src-components-background-template-tsx","path":"/game:garou-mark-of-the-wolves/grant/fullscreen","webpackCompilationHash":"d74d74fcb85cf1ca7c80","result":{"data":{"currentLevel":{"levelName":"Grant","gameNameUsa":"Garou: Mark of the Wolves","developer":"SNK","system":"Neo Geo","year":1999,"series":"Fatal Fury"},"prevLevel":{"levelName":"Town","gameNameUsa":"The Last Blade"},"nextLevel":{"levelName":"Fei Long","gameNameUsa":"Super Street Fighter 2 Turbo"},"mainImg":{"publicURL":"/static/motw_grant-8341f934bb48a8effca6c0686e6467cd.gif"},"bgImg":{"childImageSharp":{"resize":{"src":"/static/263279951aa66c328a5cdbe2a317d04f/ad8a7/motw_grant_static.jpg"}}},"twitterImg":{"childImageSharp":{"resize":{"src":"/static/263279951aa66c328a5cdbe2a317d04f/e7081/motw_grant_static.jpg"}}},"dimensions":{"width":"640","height":"384"}},"pageContext":{"isCreatedByStatefulCreatePages":false,"currentId":276,"nextId":136,"prevId":152,"mainImageRelativePath":"bgs/full/motw_grant.gif","bgImageRelativePath":"bgs/static/motw_grant_static.jpg","mainImageRegex":"/motw_grant.gif/","fullscreen":true}}}