{"componentChunkName":"component---src-components-background-template-tsx","path":"/game:kabuki-klash/togakushi-tsunade","webpackCompilationHash":"bbe5a206d72004b54987","result":{"data":{"currentLevel":{"levelName":"Togakushi (Tsunade)","gameNameUsa":"Kabuki Klash","developer":"Hudson","system":"Neo Geo","year":1995,"series":"Kabuki Klash"},"prevLevel":{"levelName":"Gen An","gameNameUsa":"Samurai Shodown"},"nextLevel":{"levelName":"Gen","gameNameUsa":"Street Fighter Alpha 3"},"mainImg":{"publicURL":"/static/kabukiKlash_waterWheel-777f4e90abf163a474e5cb31cde7ce51.gif"},"bgImg":{"childImageSharp":{"resize":{"src":"/static/86df333ff26c5623b75f56cb78d0c81c/ad8a7/kabukiKlash_waterWheel_static.jpg"}}},"twitterImg":{"childImageSharp":{"resize":{"src":"/static/86df333ff26c5623b75f56cb78d0c81c/e7081/kabukiKlash_waterWheel_static.jpg"}}},"dimensions":{"width":"624","height":"224"}},"pageContext":{"isCreatedByStatefulCreatePages":false,"currentId":163,"nextId":124,"prevId":226,"mainImageRelativePath":"bgs/full/kabukiKlash_waterWheel.gif","bgImageRelativePath":"bgs/static/kabukiKlash_waterWheel_static.jpg","mainImageRegex":"/kabukiKlash_waterWheel.gif/"}}}