{"componentChunkName":"component---src-components-background-template-tsx","path":"/game:garou-mark-of-the-wolves/rock-howard/fullscreen","webpackCompilationHash":"08ee93708f3b0f80b00c","result":{"data":{"currentLevel":{"levelName":"Rock Howard","gameNameUsa":"Garou: Mark of the Wolves","developer":"SNK","system":"Neo Geo","year":1999,"series":"Fatal Fury","ripCredit":null,"ripCreditUrl":null},"prevLevel":{"levelName":"Fireworks","gameNameUsa":"Art of Fighting 3"},"nextLevel":{"levelName":"Rai","gameNameUsa":"Waku Waku 7"},"mainImg":{"publicURL":"/static/motw_downtown-cb25d556c94dde722c37d5cad1c924a6.gif"},"bgImg":{"childImageSharp":{"resize":{"src":"/static/dbc153d58e74ae4e7407a1844980ccdd/ad8a7/motw_downtown_static.jpg"}}},"twitterImg":{"childImageSharp":{"fixed":{"src":"/static/dbc153d58e74ae4e7407a1844980ccdd/792e8/motw_downtown_static.jpg"}}},"dimensions":{"width":"621","height":"370"}},"pageContext":{"isCreatedByStatefulCreatePages":false,"currentId":28,"nextId":322,"prevId":254,"mainImageRelativePath":"bgs/full/motw_downtown.gif","bgImageRelativePath":"bgs/static/motw_downtown_static.jpg","mainImageRegex":"/motw_downtown.gif/","fullscreen":true}}}