{"componentChunkName":"component---src-components-background-template-tsx","path":"/game:street-fighter-alpha-3/mykonos-island-cammy","webpackCompilationHash":"be3257431df42ebf1d66","result":{"data":{"currentLevel":{"levelName":"Mykonos Island (Cammy)","gameNameUsa":"Street Fighter Alpha 3","developer":"Capcom","system":"CPS2","year":1998,"series":"Street Fighter","ripCredit":null,"ripCreditUrl":null},"prevLevel":{"levelName":"Gas Station","gameNameUsa":"Art of Fighting 3"},"nextLevel":{"levelName":"Susano","gameNameUsa":"Ragnagard"},"mainImg":{"publicURL":"/static/sfa3_cammy-c89b64d9373ebcdb17be7881c6fb46b4.gif"},"bgImg":{"childImageSharp":{"resize":{"src":"/static/b13286e1d87a13c0d66868f6aa60601d/ad8a7/sfa3_cammy_static.jpg"}}},"twitterImg":{"childImageSharp":{"fixed":{"src":"/static/b13286e1d87a13c0d66868f6aa60601d/792e8/sfa3_cammy_static.jpg"}}},"dimensions":{"width":"750","height":"224"}},"pageContext":{"isCreatedByStatefulCreatePages":false,"currentId":122,"nextId":332,"prevId":11,"mainImageRelativePath":"bgs/full/sfa3_cammy.gif","bgImageRelativePath":"bgs/static/sfa3_cammy_static.jpg","mainImageRegex":"/sfa3_cammy.gif/"}}}