{"componentChunkName":"component---src-components-background-template-tsx","path":"/game:fatal-fury/happy-park/fullscreen","webpackCompilationHash":"d07aa72cf7e154906db2","result":{"data":{"currentLevel":{"levelName":"Happy Park","gameNameUsa":"Fatal Fury","developer":"SNK","system":"Neo Geo","year":1991,"series":"Fatal Fury"},"prevLevel":{"levelName":"Tokyo","gameNameUsa":"The King of Fighters '96"},"nextLevel":{"levelName":"Birdie","gameNameUsa":"Street Fighter Alpha"},"mainImg":{"publicURL":"/static/ff_happyPark-f9d4d34520612671d7c6604c19016777.gif"},"bgImg":{"childImageSharp":{"resize":{"src":"/static/c6624cca8f938cc14921490cb741ef4e/ad8a7/ff_happyPark_static.jpg"}}},"twitterImg":{"childImageSharp":{"resize":{"src":"/static/c6624cca8f938cc14921490cb741ef4e/e7081/ff_happyPark_static.jpg"}}},"dimensions":{"width":"619","height":"224"}},"pageContext":{"isCreatedByStatefulCreatePages":false,"currentId":179,"nextId":209,"prevId":57,"mainImageRelativePath":"bgs/full/ff_happyPark.gif","bgImageRelativePath":"bgs/static/ff_happyPark_static.jpg","mainImageRegex":"/ff_happyPark.gif/","fullscreen":true}}}