{"componentChunkName":"component---src-components-background-template-tsx","path":"/game:samurai-shodown-ii/nakoruru","webpackCompilationHash":"1f0e2efc2765151432b6","result":{"data":{"currentLevel":{"levelName":"Nakoruru","gameNameUsa":"Samurai Shodown II","developer":"SNK","system":"Neo Geo","year":1994,"series":"Samurai Shodown"},"prevLevel":{"levelName":"Castle","gameNameUsa":"Neo Geo Battle Coliseum"},"nextLevel":{"levelName":"Yang","gameNameUsa":"Street Fighter 3: 3rd Strike"},"mainImg":{"publicURL":"/static/ss2_nakoruru-cc1c1cfa81fd7a590b7190e848fda272.gif"},"bgImg":{"childImageSharp":{"resize":{"src":"/static/bd1b14105552e2e8a5a7c339416edef4/ad8a7/ss2_nakoruru_static.jpg"}}},"dimensions":{"width":"640","height":"407"}},"pageContext":{"isCreatedByStatefulCreatePages":false,"currentId":"c1e24d7f-65ef-5151-96da-cc4766d38221","prevId":"70ce653f-4a13-540c-84b9-657c066d9303","nextId":"fc5f69b1-b979-5917-8533-75d49f4bceb1","mainImageRelativePath":"bgs/full/ss2_nakoruru.gif","bgImageRelativePath":"bgs/static/ss2_nakoruru_static.jpg","mainImageRegex":"/ss2_nakoruru.gif/"}}}