{"componentChunkName":"component---src-components-background-template-tsx","path":"/game:ragnagard/chichi-nene","webpackCompilationHash":"be3257431df42ebf1d66","result":{"data":{"currentLevel":{"levelName":"Chichi-Nene","gameNameUsa":"Ragnagard","developer":"Saurus","system":"Neo Geo","year":1996,"series":"none","ripCredit":null,"ripCreditUrl":null},"prevLevel":{"levelName":"Houses at night","gameNameUsa":"The Last Blade"},"nextLevel":{"levelName":"West Subway","gameNameUsa":"Real Bout Fatal Fury"},"mainImg":{"publicURL":"/static/ragnagard_chichiNene-f6fa5b38f5ed355e6f2c0ea4f92fcc88.gif"},"bgImg":{"childImageSharp":{"resize":{"src":"/static/92fa4a88e8117abe8e96cbe69b184a44/ad8a7/ragnagard_chichiNene_static.jpg"}}},"twitterImg":{"childImageSharp":{"fixed":{"src":"/static/92fa4a88e8117abe8e96cbe69b184a44/792e8/ragnagard_chichiNene_static.jpg"}}},"dimensions":{"width":"912","height":"353"}},"pageContext":{"isCreatedByStatefulCreatePages":false,"currentId":300,"nextId":361,"prevId":147,"mainImageRelativePath":"bgs/full/ragnagard_chichiNene.gif","bgImageRelativePath":"bgs/static/ragnagard_chichiNene_static.jpg","mainImageRegex":"/ragnagard_chichiNene.gif/"}}}