{"componentChunkName":"component---src-components-background-template-tsx","path":"/game:fatal-fury/howard-arena/fullscreen","webpackCompilationHash":"be3257431df42ebf1d66","result":{"data":{"currentLevel":{"levelName":"Howard Arena","gameNameUsa":"Fatal Fury","developer":"SNK","system":"Neo Geo","year":1991,"series":"Fatal Fury","ripCredit":null,"ripCreditUrl":null},"prevLevel":{"levelName":"China","gameNameUsa":"The King of Fighters 2003"},"nextLevel":{"levelName":"Gas Station","gameNameUsa":"Art of Fighting 3"},"mainImg":{"publicURL":"/static/ff_howardArena-00443e35a6629e0e3e9624b9705a496c.gif"},"bgImg":{"childImageSharp":{"resize":{"src":"/static/9fb01e696652853f05e5cec933823c91/ad8a7/ff_howardArena_static.jpg"}}},"twitterImg":{"childImageSharp":{"fixed":{"src":"/static/9fb01e696652853f05e5cec933823c91/792e8/ff_howardArena_static.jpg"}}},"dimensions":{"width":"619","height":"236"}},"pageContext":{"isCreatedByStatefulCreatePages":false,"currentId":180,"nextId":11,"prevId":78,"mainImageRelativePath":"bgs/full/ff_howardArena.gif","bgImageRelativePath":"bgs/static/ff_howardArena_static.jpg","mainImageRegex":"/ff_howardArena.gif/","fullscreen":true}}}