{"componentChunkName":"component---src-components-background-template-tsx","path":"/game:the-king-of-fighters-94/rugal","webpackCompilationHash":"370789d7c211c9a3b82b","result":{"data":{"currentLevel":{"levelName":"Rugal","gameNameUsa":"The King of Fighters '94","developer":"SNK","system":"Neo Geo","year":1994,"series":"King of Fighters"},"prevLevel":{"levelName":"Nakoruru","gameNameUsa":"Samurai Shodown II"},"nextLevel":{"levelName":"Guy","gameNameUsa":"Street Fighter Alpha 3"},"mainImg":{"publicURL":"/static/kof94_rugal-d0fe0fdf2f03c7d986eb868f91a6242a.gif"},"bgImg":{"childImageSharp":{"resize":{"src":"/static/afc4254daf6df221e131b740a54fe3c4/ad8a7/kof94_rugal_static.jpg"}}},"dimensions":{"width":"768","height":"259"}},"pageContext":{"isCreatedByStatefulCreatePages":false,"currentId":51,"nextId":126,"prevId":99,"mainImageRelativePath":"bgs/full/kof94_rugal.gif","bgImageRelativePath":"bgs/static/kof94_rugal_static.jpg","mainImageRegex":"/kof94_rugal.gif/"}}}