{"componentChunkName":"component---src-components-background-template-tsx","path":"/game:street-fighter-alpha-3/market","webpackCompilationHash":"d07aa72cf7e154906db2","result":{"data":{"currentLevel":{"levelName":"Market","gameNameUsa":"Street Fighter Alpha 3","developer":"Capcom","system":"CPS2","year":1998,"series":"Street Fighter"},"prevLevel":{"levelName":"Joe Higashi","gameNameUsa":"Fatal Fury 2"},"nextLevel":{"levelName":"Guy","gameNameUsa":"Street Fighter Alpha 3"},"mainImg":{"publicURL":"/static/sfa3_market-bc36e6b412185ea9ecda5b0be4bdc88c.gif"},"bgImg":{"childImageSharp":{"resize":{"src":"/static/4f26f12dc587b889f9e33d977017f63b/ad8a7/sfa3_market_static.jpg"}}},"twitterImg":{"childImageSharp":{"resize":{"src":"/static/4f26f12dc587b889f9e33d977017f63b/e7081/sfa3_market_static.jpg"}}},"dimensions":{"width":"740","height":"224"}},"pageContext":{"isCreatedByStatefulCreatePages":false,"currentId":123,"nextId":126,"prevId":16,"mainImageRelativePath":"bgs/full/sfa3_market.gif","bgImageRelativePath":"bgs/static/sfa3_market_static.jpg","mainImageRegex":"/sfa3_market.gif/"}}}