{"componentChunkName":"component---src-components-background-template-tsx","path":"/game:super-street-fighter-2-turbo/fei-long","webpackCompilationHash":"393605cda4bb3bcd9d5e","result":{"data":{"currentLevel":{"levelName":"Fei Long","gameNameUsa":"Super Street Fighter 2 Turbo","developer":"Capcom","system":"CPS2","year":1994,"series":"Street Fighter"},"prevLevel":{"levelName":"Musashi","gameNameUsa":"The Last Blade"},"nextLevel":{"levelName":"Rugal","gameNameUsa":"The King of Fighters '94"},"mainImg":{"publicURL":"/static/ssf2t_feiLong-f4fe494b025dbc400a6af9d70070013d.gif"},"bgImg":{"childImageSharp":{"resize":{"src":"/static/b50e999ebc7f1163610d4097a1a5e22a/ad8a7/ssf2t_feiLong_static.jpg"}}},"dimensions":{"width":"695","height":"224"}},"pageContext":{"isCreatedByStatefulCreatePages":false,"currentId":136,"nextId":51,"prevId":154,"mainImageRelativePath":"bgs/full/ssf2t_feiLong.gif","bgImageRelativePath":"bgs/static/ssf2t_feiLong_static.jpg","mainImageRegex":"/ssf2t_feiLong.gif/"}}}