{"componentChunkName":"component---src-components-background-template-tsx","path":"/game:fatal-fury-2/billy-kane/fullscreen","webpackCompilationHash":"be3257431df42ebf1d66","result":{"data":{"currentLevel":{"levelName":"Billy Kane","gameNameUsa":"Fatal Fury 2","developer":"SNK","system":"Neo Geo","year":1992,"series":"Fatal Fury","ripCredit":null,"ripCreditUrl":null},"prevLevel":{"levelName":"Chinese Kitchen","gameNameUsa":"The King of Fighters '99"},"nextLevel":{"levelName":"Gokuu","gameNameUsa":"Ragnagard"},"mainImg":{"publicURL":"/static/ff2_billyKane-6aeaa5fc86a2c22db0e2be12e231137a.gif"},"bgImg":{"childImageSharp":{"resize":{"src":"/static/25df7361b4bed90e9e34425747418d90/ad8a7/ff2_billyKane_static.jpg"}}},"twitterImg":{"childImageSharp":{"fixed":{"src":"/static/25df7361b4bed90e9e34425747418d90/792e8/ff2_billyKane_static.jpg"}}},"dimensions":{"width":"624","height":"224"}},"pageContext":{"isCreatedByStatefulCreatePages":false,"currentId":17,"nextId":301,"prevId":366,"mainImageRelativePath":"bgs/full/ff2_billyKane.gif","bgImageRelativePath":"bgs/static/ff2_billyKane_static.jpg","mainImageRegex":"/ff2_billyKane.gif/","fullscreen":true}}}